trajectorypy/__init__.py
trajectorypy/trajectory.py
trajectorypy-1.0.0a5.dist-info/DESCRIPTION.rst
trajectorypy-1.0.0a5.dist-info/METADATA
trajectorypy-1.0.0a5.dist-info/RECORD
trajectorypy-1.0.0a5.dist-info/WHEEL
trajectorypy-1.0.0a5.dist-info/metadata.json
trajectorypy-1.0.0a5.dist-info/top_level.txt
