Metadata-Version: 2.0
Name: trajectorypy
Version: 1.0.0a5
Summary: trajectorypy is a library to track a phase state object that leaves a trajectory
Home-page: https://github.com/ggsato/trajectorypy
Author: Takenori Sato
Author-email: takenori.sato@gmail.com
License: MIT
Keywords: object tracking,kalman filtering,computer vision
Platform: UNKNOWN
Classifier: Development Status :: 3 - Alpha
Classifier: Intended Audience :: Developers
Classifier: Topic :: Software Development :: Libraries
Classifier: License :: OSI Approved :: MIT License
Classifier: Programming Language :: Python :: 2.7
Requires-Python: >=2.7
Requires-Dist: filterpy (==1.4.0)
